meltano_target_cratedb-0.0.2.dist-info/licenses/LICENSE
target_cratedb/__init__.py
target_cratedb/connector.py
target_cratedb/sinks.py
target_cratedb/target.py
target_cratedb/sqlalchemy/__init__.py
target_cratedb/sqlalchemy/patch.py
target_cratedb/tests/__init__.py
target_cratedb/tests/test_standard_target.py
meltano_target_cratedb-0.0.2.dist-info/METADATA
meltano_target_cratedb-0.0.2.dist-info/WHEEL
meltano_target_cratedb-0.0.2.dist-info/entry_points.txt
meltano_target_cratedb-0.0.2.dist-info/top_level.txt
meltano_target_cratedb-0.0.2.dist-info/RECORD
