Metadata-Version: 2.4
Name: meltano-target-cratedb
Version: 0.0.2
Summary: A Singer target / Meltano loader for CrateDB, built with the Meltano SDK, and based on the Meltano PostgreSQL target.
Author-email: Andreas Motl <andreas.motl@crate.io>
License-Expression: MIT
Project-URL: changelog, https://github.com/crate/meltano-target-cratedb/blob/main/CHANGES.md
Project-URL: documentation, https://github.com/crate/meltano-target-cratedb
Project-URL: issues, https://github.com/crate/meltano-target-cratedb/issues
Project-URL: repository, https://github.com/crate/meltano-target-cratedb
Keywords: CrateDB,data,data-toolkit,ELT,ETL,extract,ingest,io,load,Meltano,Meltano SDK,pipeline,Postgres,PostgreSQL,process,Singer,SQL,SQLAlchemy,transfer,transformation
Classifier: Development Status :: 3 - Alpha
Classifier: Environment :: Console
Classifier: Intended Audience :: Customer Service
Classifier: Intended Audience :: Developers
Classifier: Intended Audience :: Education
Classifier: Intended Audience :: End Users/Desktop
Classifier: Intended Audience :: Information Technology
Classifier: Intended Audience :: Manufacturing
Classifier: Intended Audience :: Science/Research
Classifier: Intended Audience :: System Administrators
Classifier: Intended Audience :: Telecommunications Industry
Classifier: Operating System :: MacOS :: MacOS X
Classifier: Operating System :: Microsoft :: Windows
Classifier: Operating System :: POSIX :: Linux
Classifier: Operating System :: Unix
Classifier: Programming Language :: Python
Classifier: Programming Language :: Python :: 3 :: Only
Classifier: Programming Language :: Python :: 3.10
Classifier: Programming Language :: Python :: 3.11
Classifier: Programming Language :: Python :: 3.12
Classifier: Programming Language :: Python :: 3.13
Classifier: Programming Language :: Python :: 3.14
Classifier: Programming Language :: SQL
Classifier: Topic :: Adaptive Technologies
Classifier: Topic :: Communications
Classifier: Topic :: Database
Classifier: Topic :: Documentation
Classifier: Topic :: Education
Classifier: Topic :: Internet
Classifier: Topic :: Office/Business
Classifier: Topic :: Scientific/Engineering
Classifier: Topic :: Software Development :: Libraries
Classifier: Topic :: Software Development :: Pre-processors
Classifier: Topic :: Software Development :: Quality Assurance
Classifier: Topic :: Software Development :: Testing
Classifier: Topic :: Software Development :: Version Control
Classifier: Topic :: System :: Archiving
Classifier: Topic :: System :: Benchmark
Classifier: Topic :: System :: Clustering
Classifier: Topic :: System :: Distributed Computing
Classifier: Topic :: System :: Logging
Classifier: Topic :: System :: Monitoring
Classifier: Topic :: System :: Networking
Classifier: Topic :: System :: Systems Administration
Classifier: Topic :: Text Processing
Classifier: Topic :: Utilities
Requires-Python: >=3.10
License-File: LICENSE
Requires-Dist: cratedb-toolkit
Requires-Dist: importlib-resources; python_version < "3.9"
Requires-Dist: meltanolabs-target-postgres<0.7,>=0.6
Requires-Dist: sqlalchemy-cratedb
Requires-Dist: verlib2<0.4
Provides-Extra: develop
Requires-Dist: black<27; extra == "develop"
Requires-Dist: mypy<1.20; extra == "develop"
Requires-Dist: poethepoet<1; extra == "develop"
Requires-Dist: pyproject-fmt<3; extra == "develop"
Requires-Dist: ruff<0.15; extra == "develop"
Requires-Dist: validate-pyproject<1; extra == "develop"
Provides-Extra: release
Requires-Dist: build<2; extra == "release"
Requires-Dist: twine<7; extra == "release"
Provides-Extra: test
Requires-Dist: meltano-tap-countries; extra == "test"
Requires-Dist: meltano-tap-fundamentals; extra == "test"
Requires-Dist: pytest<10; extra == "test"
Requires-Dist: pytest-cov<8; extra == "test"
Requires-Dist: pytest-mock<4; extra == "test"
Dynamic: license-file
